{
    "timezone": "-0600",

    "ref": "2012-01-09, 08:00",

    "events": {
        "semEnd": {
            "time": "2012-05-04, 17:00",
            "phrase": "left in the semester.",
            "ref": "2012-01-09, 08:00"
        },

        "sprBreak": {
            "time": "2012-03-09, 17:00",
            "phrase": "until Spring break.",
            "name": "Spring Break"
        },

        "veishea": {
            "time": "2012-04-16, 08:00",
            "phrase": "until VEISHEA!",
            "name": "VEISHEA"
        }
    }
}
